LICENSE
MANIFEST.in
README.rst
requirements.txt
setup.py
wikipedia/__init__.py
wikipedia/exceptions.py
wikipedia/util.py
wikipedia/wikipedia.py
wikipedia_sections.egg-info/PKG-INFO
wikipedia_sections.egg-info/SOURCES.txt
wikipedia_sections.egg-info/dependency_links.txt
wikipedia_sections.egg-info/requires.txt
wikipedia_sections.egg-info/top_level.txt