Metadata-Version: 1.1
Name: wikipedia-sections
Version: 2.0.0
Summary: Wikipedia API for Python extracting sections
Home-page: https://github.com/sachavakili/Wikipedia
Author: Sacha Vakili
Author-email: vakili.sacha@gmail.com
License: MIT
Download-URL: https://github.com/sachavakili/Wikipedia/archive/v2.0.tar.gz
Keywords: python wikipedia API
Platform: UNKNOWN
Classifier: Development Status :: 4 - Beta
Classifier: Topic :: Software Development :: Libraries
Classifier: License :: OSI Approved :: MIT License
Classifier: Programming Language :: Python
Classifier: Programming Language :: Python :: 3
